basicbaarutils/__init__.py
basicbaarutils/cron_trigger.py
basicbaarutils/progressbar.py
basicbaarutil-0.0.2.dist-info/LICENSE
basicbaarutil-0.0.2.dist-info/METADATA
basicbaarutil-0.0.2.dist-info/WHEEL
basicbaarutil-0.0.2.dist-info/top_level.txt
basicbaarutil-0.0.2.dist-info/RECORD
