Metadata-Version: 2.1
Name: basicbaarutil
Version: 0.0.2
Summary: Basic util library for BAAR related operation
Author: Pritam Sarkar (Baar Technologies)
Author-email: <pritamsarkar84028220@gmail.com>
Keywords: python,basicbaarutil,quartz,quartzcron,quartz cron,cron,cron triggers,quartzcron triggers
Classifier: Development Status :: 1 - Planning
Classifier: Intended Audience :: Developers
Classifier: Programming Language :: Python :: 3
Classifier: Operating System :: Unix
Classifier: Operating System :: MacOS :: MacOS X
Classifier: Operating System :: Microsoft :: Windows
License-File: LICENSE
Requires-Dist: colorama >=0.4.6
Requires-Dist: cron-schedule-triggers >=0.0.11
